cfn_resource_provider_schemas/__init__.py
cfn_resource_provider_schemas/Accessanalyzer/Analyzer.py
cfn_resource_provider_schemas/Accessanalyzer/__init__.py
cfn_resource_provider_schemas/Acmpca/Certificate.py
cfn_resource_provider_schemas/Acmpca/Certificateauthority.py
cfn_resource_provider_schemas/Acmpca/Certificateauthorityactivation.py
cfn_resource_provider_schemas/Acmpca/Permission.py
cfn_resource_provider_schemas/Acmpca/__init__.py
cfn_resource_provider_schemas/Alexa/Askskill.py
cfn_resource_provider_schemas/Alexa/__init__.py
cfn_resource_provider_schemas/Amazonmq/Broker.py
cfn_resource_provider_schemas/Amazonmq/Configuration.py
cfn_resource_provider_schemas/Amazonmq/Configurationassociation.py
cfn_resource_provider_schemas/Amazonmq/__init__.py
cfn_resource_provider_schemas/Amplify/App.py
cfn_resource_provider_schemas/Amplify/Branch.py
cfn_resource_provider_schemas/Amplify/Domain.py
cfn_resource_provider_schemas/Amplify/__init__.py
cfn_resource_provider_schemas/Amplifyuibuilder/Component.py
cfn_resource_provider_schemas/Amplifyuibuilder/Form.py
cfn_resource_provider_schemas/Amplifyuibuilder/Theme.py
cfn_resource_provider_schemas/Amplifyuibuilder/__init__.py
cfn_resource_provider_schemas/Apigateway/Account.py
cfn_resource_provider_schemas/Apigateway/Apikey.py
cfn_resource_provider_schemas/Apigateway/Authorizer.py
cfn_resource_provider_schemas/Apigateway/Basepathmapping.py
cfn_resource_provider_schemas/Apigateway/Basepathmappingv2.py
cfn_resource_provider_schemas/Apigateway/Clientcertificate.py
cfn_resource_provider_schemas/Apigateway/Deployment.py
cfn_resource_provider_schemas/Apigateway/Documentationpart.py
cfn_resource_provider_schemas/Apigateway/Documentationversion.py
cfn_resource_provider_schemas/Apigateway/Domainname.py
cfn_resource_provider_schemas/Apigateway/Domainnameaccessassociation.py
cfn_resource_provider_schemas/Apigateway/Domainnamev2.py
cfn_resource_provider_schemas/Apigateway/Gatewayresponse.py
cfn_resource_provider_schemas/Apigateway/Method.py
cfn_resource_provider_schemas-25.5.2.dist-info/METADATA
cfn_resource_provider_schemas-25.5.2.dist-info/WHEEL
cfn_resource_provider_schemas-25.5.2.dist-info/RECORD
