Metadata-Version: 2.4
Name: cfn-resource-provider-schemas
Version: 25.5.2
Summary: AWS CFN Resource Properties JSON Schema definitions
Project-URL: Repository, https://github.com/morph027/cfn-resource-provider-schemas
Author-email: Stefan Heitmüller <stefan.heitmueller@gmx.com>
Requires-Python: >=3.11
